mkname/__init__.py
mkname/__main__.py
mkname/cli.py
mkname/constants.py
mkname/db.py
mkname/exceptions.py
mkname/init.py
mkname/mkname.py
mkname/mod.py
mkname/model.py
mkname/py.typed
mkname/tools.py
mkname/utility.py
mkname/data/__init__.py
mkname/data/defaults.cfg
mkname/data/mkname_epilogue.txt
mkname/data/names.db
mkname-0.2.5.dist-info/licenses/LICENSE
mkname-0.2.5.dist-info/METADATA
mkname-0.2.5.dist-info/WHEEL
mkname-0.2.5.dist-info/entry_points.txt
mkname-0.2.5.dist-info/top_level.txt
mkname-0.2.5.dist-info/RECORD
