Metadata-Version: 2.4
Name: mkname
Version: 0.2.5
Summary: A random name generation script.
Author-email: "Paul J. Iutzi" <pji@mac.com>
Project-URL: Homepage, https://github.com/pji/mkname
Project-URL: Documentation, https://mkname.readthedocs.io
Project-URL: Source, https://github.com/pji/mkname
Classifier: Programming Language :: Python :: 3
Classifier: License :: OSI Approved :: MIT License
Classifier: Operating System :: OS Independent
Requires-Python: <4.0,>=3.10
License-File: LICENSE
Requires-Dist: yadr
Dynamic: license-file
